fastspider/VERSION
fastspider/__init__.py
fastspider/requirements.txt
fastspider/start.py
fastspider/cache/__init__.py
fastspider/cache/item_cache.py
fastspider/cache/redis_cache.py
fastspider/cache/request_cache.py
fastspider/commands/__init__.py
fastspider/commands/cmdline.py
fastspider/commands/create_builder.py
fastspider/commands/crawl/__init__.py
fastspider/commands/crawl/run_spider.py
fastspider/commands/create/__init__.py
fastspider/commands/create/create_project.py
fastspider/commands/create/create_spider.py
fastspider/core/__init__.py
fastspider/core/base/__init__.py
fastspider/core/base/cycle_base.py
fastspider/core/base/light_base.py
fastspider/core/controller/__init__.py
fastspider/core/controller/collector.py
fastspider/core/controller/controller.py
fastspider/core/controller/spider_controller.py
fastspider/core/scheduler/__init__.py
fastspider/core/scheduler/scheduler.py
fastspider/core/spiders/__init__.py
fastspider/core/spiders/light_spider.py
fastspider/core/spiders/spider.py
fastspider/db/__init__.py
fastspider/db/memory_db.py
fastspider/db/mysql_db.py
fastspider/db/redis_db.py
fastspider/http/__init__.py
fastspider/http/selector.py
fastspider/http/user_agent.py
fastspider/http/fastselenium/__init__.py
fastspider/http/fastselenium/fastwebdriver.py
fastspider/http/request/__init__.py
fastspider/http/request/request.py
fastspider/http/response/__init__.py
fastspider/http/response/response.py
fastspider/item/__init__.py
fastspider/item/item.py
fastspider/pipeline/__init__.py
fastspider/pipeline/base_pipeline.py
fastspider/pipeline/mysql_pipeline.py
fastspider/pipeline/redis_pipeline.py
fastspider/settings/__init__.py
fastspider/settings/common.py
fastspider/templates/spiders/light_spider.tmpl
fastspider/templates/spiders/spider.tmpl
fastspider/utils/__init__.py
fastspider/utils/logger.py
fastspider/utils/tools.py
fastspider/waring/__init__.py
fastspider/waring/feishu.py
fastspider-1.0.36.dist-info/LICENSE
fastspider-1.0.36.dist-info/METADATA
fastspider-1.0.36.dist-info/WHEEL
fastspider-1.0.36.dist-info/entry_points.txt
fastspider-1.0.36.dist-info/top_level.txt
fastspider-1.0.36.dist-info/RECORD
